{
  "Сроки": [
    "срок",
    "задерж",
    "долго",
    "быстро",
    "оперативно",
    "ожидан",
    "перенесли",
    "не успели",
    "месяц",
    "неделя"
  ],
  "Стоимость": [
    "стоимость",
    "цена",
    "дорого",
    "дешево",
    "смета",
    "расчет",
    "оплата",
    "договор",
    "деньги",
    "переплата"
  ],
  "Документы": [
    "документ",
    "акт",
    "договор",
    "смета",
    "проект",
    "чертеж",
    "отчет",
    "заключение",
    "разрешение",
    "паспорт"
  ],
  "Коммуникация": [
    "менеджер",
    "специалист",
    "ответ",
    "позвонили",
    "связались",
    "общение",
    "консультация",
    "объяснили",
    "поддержка",
    "звонок"
  ],
  "Качество работ": [
    "качество",
    "работа",
    "монтаж",
    "ремонт",
    "ошибка",
    "дефект",
    "замечание",
    "проверка",
    "контроль",
    "переделка"
  ],
  "Объект строительства": [
    "дом",
    "квартира",
    "здание",
    "объект",
    "стройка",
    "жилой комплекс",
    "помещение",
    "офис",
    "фасад",
    "кровля"
  ]
}